search_base64/__init__.py
search_base64/find.py
search_base64-0.0.1.dist-info/METADATA
search_base64-0.0.1.dist-info/WHEEL
search_base64-0.0.1.dist-info/top_level.txt
search_base64-0.0.1.dist-info/RECORD
