Metadata-Version: 2.1
Name: search-base64
Version: 0.0.1
Summary: Package to search for clear text in base64-encoded test
Project-URL: Homepage, https://github.com/erakem/searchBase64
Project-URL: Bug Tracker, https://github.com/erakem/searchBase64/issues
Keywords: base64
Classifier: Programming Language :: Python
Classifier: Programming Language :: Python :: 3
